{
    "payload": {
        "dropsources": [
            {
                "type": "mission",
                "item": "54a74455e779892d5e5156cd",
                "location": "62d2eb3b75156700663c8361",
                "mission": "62d2f073751567007abb196f",
                "rate": 10.0,
                "rarity": "uncommon",
                "rotation": "b",
                "id": "62d35255650ea601a7ad18ba"
            },
            {
                "type": "npc",
                "item": "54a74455e779892d5e5156cd",
                "npc": "62d2f02e751567007abb185d",
                "rate": 1.9,
                "rarity": "common",
                "id": "62d35255650ea601a7ad18bb"
            },
            {
                "type": "npc",
                "item": "54a74455e779892d5e5156cd",
                "npc": "62d2f020751567007abb17f0",
                "rate": 1.9,
                "rarity": "common",
                "id": "62d35255650ea601a7ad18bf"
            },
            {
                "type": "npc",
                "item": "54a74455e779892d5e5156cd",
                "npc": "62d2f02e751567007abb1862",
                "rate": 0.76,
                "rarity": "uncommon",
                "id": "62d35255650ea601a7ad18c1"
            },
            {
                "type": "npc",
                "item": "54a74455e779892d5e5156cd",
                "npc": "62d2eff7751567007abb169f",
                "rate": 0.76,
                "rarity": "uncommon",
                "id": "62d35255650ea601a7ad18c2"
            },
            {
                "type": "npc",
                "item": "54a74455e779892d5e5156cd",
                "npc": "62d2f03c751567007abb18e3",
                "rate": 0.76,
                "rarity": "uncommon",
                "id": "62d35255650ea601a7ad18c3"
            },
            {
                "type": "npc",
                "item": "54a74455e779892d5e5156cd",
                "npc": "62d2f010751567007abb1771",
                "rate": 11.38,
                "rarity": "common",
                "id": "62d35255650ea601a7ad18c6"
            },
            {
                "type": "npc",
                "item": "54a74455e779892d5e5156cd",
                "npc": "62d2f037751567007abb18ac",
                "rate": 2.85,
                "rarity": "common",
                "id": "62d35255650ea601a7ad18c7"
            },
            {
                "type": "npc",
                "item": "54a74455e779892d5e5156cd",
                "npc": "62d2effb751567007abb16c7",
                "rate": 2.85,
                "rarity": "common",
                "id": "62d35255650ea601a7ad18c8"
            },
            {
                "type": "npc",
                "item": "54a74455e779892d5e5156cd",
                "npc": "62d2f01e751567007abb17e4",
                "rate": 1.9,
                "rarity": "common",
                "id": "62d35255650ea601a7ad18c9"
            },
            {
                "type": "npc",
                "item": "54a74455e779892d5e5156cd",
                "npc": "62d2f046751567007abb193a",
                "rate": 3.79,
                "rarity": "common",
                "id": "62d35255650ea601a7ad18ca"
            },
            {
                "type": "npc",
                "item": "54a74455e779892d5e5156cd",
                "npc": "62d2f044751567007abb1930",
                "rate": 1.9,
                "rarity": "common",
                "id": "62d35255650ea601a7ad18cc"
            },
            {
                "type": "npc",
                "item": "54a74455e779892d5e5156cd",
                "npc": "62d2f032751567007abb1883",
                "rate": 0.76,
                "rarity": "uncommon",
                "id": "62d35255650ea601a7ad18cd"
            },
            {
                "type": "npc",
                "item": "54a74455e779892d5e5156cd",
                "npc": "62d2f03a751567007abb18c7",
                "rate": 1.9,
                "rarity": "common",
                "id": "62d35255650ea601a7ad18ce"
            },
            {
                "type": "npc",
                "item": "54a74455e779892d5e5156cd",
                "npc": "62d2f037751567007abb18af",
                "rate": 1.9,
                "rarity": "common",
                "id": "62d35255650ea601a7ad18cf"
            },
            {
                "type": "npc",
                "item": "54a74455e779892d5e5156cd",
                "npc": "62d2effc751567007abb16cd",
                "rate": 1.9,
                "rarity": "common",
                "id": "62d35255650ea601a7ad18d0"
            },
            {
                "type": "npc",
                "item": "54a74455e779892d5e5156cd",
                "npc": "62d2f00f751567007abb176a",
                "rate": 1.26,
                "rarity": "uncommon",
                "id": "62d35255650ea601a7ad18d1"
            },
            {
                "type": "npc",
                "item": "54a74455e779892d5e5156cd",
                "npc": "62d2f019751567007abb17c0",
                "rate": 1.26,
                "rarity": "uncommon",
                "id": "62d35255650ea601a7ad18d2"
            },
            {
                "type": "npc",
                "item": "54a74455e779892d5e5156cd",
                "npc": "62d2effc751567007abb16cc",
                "rate": 1.9,
                "rarity": "common",
                "id": "62d35255650ea601a7ad18d3"
            },
            {
                "type": "npc",
                "item": "54a74455e779892d5e5156cd",
                "npc": "62d2f009751567007abb173a",
                "rate": 1.9,
                "rarity": "common",
                "id": "62d35255650ea601a7ad18d4"
            },
            {
                "type": "npc",
                "item": "54a74455e779892d5e5156cd",
                "npc": "62d2f03a751567007abb18c5",
                "rate": 1.9,
                "rarity": "common",
                "id": "62d35255650ea601a7ad18d5"
            },
            {
                "type": "npc",
                "item": "54a74455e779892d5e5156cd",
                "npc": "62d2f021751567007abb17f5",
                "rate": 1.9,
                "rarity": "common",
                "id": "62d35255650ea601a7ad18d6"
            },
            {
                "type": "npc",
                "item": "54a74455e779892d5e5156cd",
                "npc": "62d2f042751567007abb191d",
                "rate": 1.9,
                "rarity": "common",
                "id": "62d35255650ea601a7ad18d7"
            },
            {
                "type": "npc",
                "item": "54a74455e779892d5e5156cd",
                "npc": "62d2f018751567007abb17bd",
                "rate": 1.9,
                "rarity": "common",
                "id": "63ee050d1012541219882857"
            },
            {
                "type": "npc",
                "item": "54a74455e779892d5e5156cd",
                "npc": "62d2f015751567007abb179f",
                "rate": 0.76,
                "rarity": "uncommon",
                "id": "63ee050d1012541219882858"
            },
            {
                "type": "npc",
                "item": "54a74455e779892d5e5156cd",
                "npc": "62d2f012751567007abb1783",
                "rate": 1.9,
                "rarity": "common",
                "id": "63ee050d1012541219882859"
            },
            {
                "type": "npc",
                "item": "54a74455e779892d5e5156cd",
                "npc": "62d2eff6751567007abb1695",
                "rate": 1.9,
                "rarity": "common",
                "id": "63f103e807ebe90061f4be20"
            }
        ]
    }
}