{"payload": {"dropsources": [{"type": "mission", "item": "641264a57d179f02190e41f3", "location": "62d2eb5b75156700663c83e4", "mission": "62d2f0a2751567007abb198b", "rate": 1.84, "rarity": "ultra_rare", "rotation": "c", "id": "641269487d179f022214f556"}, {"type": "mission", "item": "641264a57d179f02190e41f3", "location": "62d2eb4a75156700663c839c", "mission": "62d2f0a2751567007abb198b", "rate": 1.84, "rarity": "ultra_rare", "rotation": "c", "id": "641269487d179f022214f557"}, {"type": "mission", "item": "641264a57d179f02190e41f3", "location": "62d2eb5475156700663c83c5", "mission": "62d2f0a2751567007abb198b", "rate": 1.84, "rarity": "ultra_rare", "rotation": "c", "id": "641269487d179f022214f558"}, {"type": "mission", "item": "641264a57d179f02190e41f3", "location": "62d2eb6275156700663c8400", "mission": "62d2f0cb751567007abb198d", "rate": 11.06, "rarity": "uncommon", "rotation": "c", "id": "641269487d179f022214f559"}, {"type": "mission", "item": "641264a57d179f02190e41f3", "location": "63ee03bd10125411f5fc6dbb", "mission": "62d2f0a2751567007abb198b", "rate": 6.25, "rarity": "rare", "rotation": "a", "id": "641269487d179f022214f55a"}, {"type": "mission", "item": "641264a57d179f02190e41f3", "location": "63ee03bd10125411f5fc6dbb", "mission": "62d2f0a2751567007abb198b", "rate": 5.8, "rarity": "rare", "rotation": "b", "id": "641269487d179f022214f55b"}, {"type": "mission", "item": "641264a57d179f02190e41f3", "location": "62d2eb4175156700663c8378", "mission": "62d2f0f5751567007abb199b", "rate": 5.56, "rarity": "rare", "rotation": "b", "id": "641269487d179f022214f55c"}, {"type": "mission", "item": "641264a57d179f02190e41f3", "location": "62d2eb7275156700663c8443", "mission": "62d2f0a2751567007abb198b", "rate": 6.25, "rarity": "rare", "rotation": "b", "id": "641269487d179f022214f55d"}, {"type": "mission", "item": "641264a57d179f02190e41f3", "location": "62d2eb7275156700663c8443", "mission": "62d2f0a2751567007abb198b", "rate": 11.06, "rarity": "uncommon", "rotation": "c", "id": "641269487d179f022214f55e"}, {"type": "mission", "item": "641264a57d179f02190e41f3", "location": "62d2eb6075156700663c83f7", "mission": "62d2f0cb751567007abb198d", "rate": 11.06, "rarity": "uncommon", "rotation": "c", "id": "641269487d179f022214f55f"}, {"type": "mission", "item": "641264a57d179f02190e41f3", "location": "62d2eb3c75156700663c8362", "mission": "62d2f073751567007abb196f", "rate": 7.14, "rarity": "rare", "rotation": "b", "id": "641269487d179f022214f560"}, {"type": "mission", "item": "641264a57d179f02190e41f3", "location": "62d2eb3c75156700663c8362", "mission": "62d2f073751567007abb196f", "rate": 14.29, "rarity": "uncommon", "rotation": "c", "id": "641269487d179f022214f561"}, {"type": "mission", "item": "641264a57d179f02190e41f3", "location": "62d2eb4575156700663c8388", "mission": "62d2f0a2751567007abb198b", "rate": 1.84, "rarity": "ultra_rare", "rotation": "c", "id": "641269487d179f022214f562"}, {"type": "mission", "item": "641264a57d179f02190e41f3", "location": "62d2eb4475156700663c8385", "mission": "62d2f0cb751567007abb198d", "rate": 11.06, "rarity": "uncommon", "rotation": "c", "id": "641269487d179f022214f563"}, {"type": "mission", "item": "641264a57d179f02190e41f3", "location": "62d2eb4f75156700663c83b1", "mission": "62d2f0a2751567007abb198b", "rate": 6.25, "rarity": "rare", "rotation": "b", "id": "641269487d179f022214f564"}, {"type": "mission", "item": "641264a57d179f02190e41f3", "location": "62d2eb4f75156700663c83b1", "mission": "62d2f0a2751567007abb198b", "rate": 11.06, "rarity": "uncommon", "rotation": "c", "id": "641269487d179f022214f565"}, {"type": "mission", "item": "641264a57d179f02190e41f3", "location": "62d2eb6275156700663c8401", "mission": "62d2f0cb751567007abb198d", "rate": 11.06, "rarity": "uncommon", "rotation": "c", "id": "641269487d179f022214f566"}, {"type": "mission", "item": "641264a57d179f02190e41f3", "location": "62d2eb5575156700663c83cb", "mission": "62d2f073751567007abb196f", "rate": 7.14, "rarity": "rare", "rotation": "b", "id": "641269487d179f022214f569"}, {"type": "mission", "item": "641264a57d179f02190e41f3", "location": "62d2eb5575156700663c83cb", "mission": "62d2f073751567007abb196f", "rate": 14.29, "rarity": "uncommon", "rotation": "c", "id": "641269487d179f022214f56a"}, {"type": "mission", "item": "641264a57d179f02190e41f3", "location": "62d2eb5c75156700663c83e5", "mission": "62d2f0cb751567007abb198d", "rate": 11.06, "rarity": "uncommon", "rotation": "c", "id": "641269487d179f022214f56b"}, {"type": "mission", "item": "641264a57d179f02190e41f3", "location": "62d2eb5f75156700663c83f5", "mission": "62d2f04a751567007abb1957", "rate": 10.0, "rarity": "uncommon", "rotation": "c", "id": "641269487d179f022214f56c"}, {"type": "mission", "item": "641264a57d179f02190e41f3", "location": "62d2eb4b75156700663c83a1", "mission": "62d2f073751567007abb196f", "rate": 7.14, "rarity": "rare", "rotation": "b", "id": "641269487d179f022214f56d"}, {"type": "mission", "item": "641264a57d179f02190e41f3", "location": "62d2eb4b75156700663c83a1", "mission": "62d2f073751567007abb196f", "rate": 14.29, "rarity": "uncommon", "rotation": "c", "id": "641269487d179f022214f56e"}, {"type": "mission", "item": "641264a57d179f02190e41f3", "location": "62d2f0fb751567007abb19b0", "mission": "62d2f0a2751567007abb198b", "rate": 10.0, "rarity": "uncommon", "rotation": "a", "event": true, "id": "641269487d179f022214f56f"}, {"type": "mission", "item": "641264a57d179f02190e41f3", "location": "62d2eb4b75156700663c839f", "mission": "62d2f0cb751567007abb198d", "rate": 6.67, "rarity": "rare", "rotation": "b", "id": "641269487d179f022214f570"}, {"type": "mission", "item": "641264a57d179f02190e41f3", "location": "62d2f105751567007abb1a10", "mission": "62d2f0cb751567007abb198d", "rate": 6.67, "rarity": "rare", "rotation": "b", "event": true, "id": "641269487d179f022214f571"}, {"type": "mission", "item": "641264a57d179f02190e41f3", "location": "62d2eb5975156700663c83dc", "mission": "62d2f0f8751567007abb19a6", "rate": 3.22, "rarity": "rare", "rotation": "b", "id": "641269487d179f022214f572"}, {"type": "mission", "item": "641264a57d179f02190e41f3", "location": "62d2f104751567007abb1a03", "mission": "62d2f0a2751567007abb198b", "rate": 10.0, "rarity": "uncommon", "rotation": "a", "event": true, "id": "641269487d179f022214f573"}, {"type": "mission", "item": "641264a57d179f02190e41f3", "location": "62d2eb5675156700663c83d0", "mission": "62d2f0f5751567007abb199b", "rate": 14.29, "rarity": "uncommon", "rotation": "b", "id": "641269487d179f022214f574"}, {"type": "mission", "item": "641264a57d179f02190e41f3", "location": "62d2eb5675156700663c83d0", "mission": "62d2f0f5751567007abb199b", "rate": 13.56, "rarity": "uncommon", "rotation": "c", "id": "641269487d179f022214f575"}, {"type": "mission", "item": "641264a57d179f02190e41f3", "location": "62d2eb3f75156700663c8370", "mission": "62d2f0a2751567007abb198b", "rate": 10.0, "rarity": "uncommon", "rotation": "a", "id": "641269487d179f022214f576"}, {"type": "mission", "item": "641264a57d179f02190e41f3", "location": "62d2eb5675156700663c83cd", "mission": "62d2f0cb751567007abb198d", "rate": 6.67, "rarity": "rare", "rotation": "b", "id": "641269487d179f022214f577"}, {"type": "mission", "item": "641264a57d179f02190e41f3", "location": "62d2eb4975156700663c8398", "mission": "62d2f0a2751567007abb198b", "rate": 10.0, "rarity": "uncommon", "rotation": "a", "id": "641269487d179f022214f578"}, {"type": "mission", "item": "641264a57d179f02190e41f3", "location": "62d2eb5475156700663c83c6", "mission": "62d2f099751567007abb197d", "rate": 6.67, "rarity": "rare", "rotation": "b", "id": "641269487d179f022214f579"}, {"type": "mission", "item": "641264a57d179f02190e41f3", "location": "62d2eb4175156700663c8376", "mission": "62d2f0f8751567007abb19a6", "rate": 3.22, "rarity": "rare", "rotation": "b", "id": "641269487d179f022214f57a"}, {"type": "mission", "item": "641264a57d179f02190e41f3", "location": "62d2eb4275156700663c837b", "mission": "62d2f04a751567007abb1957", "rate": 10.0, "rarity": "uncommon", "rotation": "b", "id": "641269487d179f022214f57b"}, {"type": "mission", "item": "641264a57d179f02190e41f3", "location": "62d2eb4b75156700663c83a0", "mission": "62d2f0cb751567007abb198d", "rate": 6.67, "rarity": "rare", "rotation": "b", "id": "641269487d179f022214f57c"}, {"type": "mission", "item": "641264a57d179f02190e41f3", "location": "62d2eb5f75156700663c83f2", "mission": "62d2f0a2751567007abb198b", "rate": 10.0, "rarity": "uncommon", "rotation": "a", "id": "641269487d179f022214f57d"}, {"type": "mission", "item": "641264a57d179f02190e41f3", "location": "62d2eb6775156700663c8416", "mission": "62d2f073751567007abb196f", "rate": 10.0, "rarity": "uncommon", "rotation": "a", "id": "641269487d179f022214f57e"}, {"type": "mission", "item": "641264a57d179f02190e41f3", "location": "62d2eb4d75156700663c83aa", "mission": "62d2f0cb751567007abb198d", "rate": 6.67, "rarity": "rare", "rotation": "b", "id": "641269487d179f022214f57f"}, {"type": "mission", "item": "641264a57d179f02190e41f3", "location": "62d2eb3e75156700663c8369", "mission": "62d2f0a2751567007abb198b", "rate": 1.84, "rarity": "ultra_rare", "rotation": "c", "id": "641269487d179f022214f580"}, {"type": "mission", "item": "641264a57d179f02190e41f3", "location": "62d2eb7175156700663c8441", "mission": "62d2f0f8751567007abb19a6", "rate": 3.22, "rarity": "rare", "rotation": "b", "id": "641269487d179f022214f581"}, {"type": "mission", "item": "641264a57d179f02190e41f3", "location": "62d2eb3e75156700663c836b", "mission": "62d2f099751567007abb197d", "rate": 6.67, "rarity": "rare", "rotation": "b", "id": "641269487d179f022214f582"}, {"type": "mission", "item": "641264a57d179f02190e41f3", "location": "62d2f0fd751567007abb19c7", "mission": "62d2f07a751567007abb1970", "rate": 4.76, "rarity": "rare", "rotation": "a", "id": "641269487d179f022214f583"}, {"type": "mission", "item": "641264a57d179f02190e41f3", "location": "62d2f105751567007abb1a11", "mission": "62d2f07a751567007abb1970", "rate": 2.41, "rarity": "rare", "id": "641269487d179f022214f584"}, {"type": "mission", "item": "641264a57d179f02190e41f3", "location": "62d2f0ff751567007abb19d4", "mission": "62d2f07a751567007abb1970", "rate": 6.67, "rarity": "rare", "rotation": "a", "id": "641269487d179f022214f585"}, {"type": "mission", "item": "641264a57d179f02190e41f3", "location": "62d2f102751567007abb19f0", "mission": "62d2f07a751567007abb1970", "rate": 6.67, "rarity": "rare", "rotation": "a", "id": "641269487d179f022214f586"}, {"type": "mission", "item": "641264a57d179f02190e41f3", "location": "62d2f0fb751567007abb19b2", "mission": "62d2f07a751567007abb1970", "rate": 2.41, "rarity": "rare", "id": "641269487d179f022214f587"}, {"type": "mission", "item": "641264a57d179f02190e41f3", "location": "62d2f0ff751567007abb19d7", "mission": "62d2f07a751567007abb1970", "rate": 10.0, "rarity": "uncommon", "rotation": "b", "id": "641269487d179f022214f588"}, {"type": "mission", "item": "641264a57d179f02190e41f3", "location": "62d2eb4c75156700663c83a6", "mission": "62d2f0cb751567007abb198d", "rate": 11.06, "rarity": "uncommon", "rotation": "c", "id": "641269487d179f022214f589"}, {"type": "mission", "item": "641264a57d179f02190e41f3", "location": "62d2eb7075156700663c843e", "mission": "62d2f0a2751567007abb198b", "rate": 1.84, "rarity": "ultra_rare", "rotation": "c", "id": "641269487d179f022214f58a"}, {"type": "mission", "item": "641264a57d179f02190e41f3", "location": "62d2f0fb751567007abb19b3", "mission": "62d2f0f8751567007abb19a6", "rate": 3.22, "rarity": "rare", "rotation": "b", "event": true, "id": "641269487d179f022214f58b"}, {"type": "mission", "item": "641264a57d179f02190e41f3", "location": "62d2eb4975156700663c8399", "mission": "62d2f0a2751567007abb198b", "rate": 10.0, "rarity": "uncommon", "rotation": "a", "id": "641269487d179f022214f58c"}, {"type": "mission", "item": "641264a57d179f02190e41f3", "location": "62d2f100751567007abb19e1", "mission": "62d2f0cb751567007abb198d", "rate": 6.67, "rarity": "rare", "rotation": "b", "event": true, "id": "641269487d179f022214f58d"}, {"type": "mission", "item": "641264a57d179f02190e41f3", "location": "62d2f0fc751567007abb19b8", "mission": "62d2f0f8751567007abb19a6", "rate": 3.22, "rarity": "rare", "rotation": "b", "event": true, "id": "641269487d179f022214f58e"}, {"type": "mission", "item": "641264a57d179f02190e41f3", "location": "62d2f100751567007abb19e2", "mission": "62d2f073751567007abb196f", "rate": 10.0, "rarity": "uncommon", "rotation": "a", "event": true, "id": "641269487d179f022214f58f"}, {"type": "mission", "item": "641264a57d179f02190e41f3", "location": "62d2f103751567007abb19fb", "mission": "62d2f0a2751567007abb198b", "rate": 10.0, "rarity": "uncommon", "rotation": "a", "event": true, "id": "641269487d179f022214f590"}, {"type": "mission", "item": "641264a57d179f02190e41f3", "location": "62d2f104751567007abb1a0c", "mission": "62d2f073751567007abb196f", "rate": 10.0, "rarity": "uncommon", "rotation": "a", "event": true, "id": "641269487d179f022214f591"}, {"type": "mission", "item": "641264a57d179f02190e41f3", "location": "62d2eb4b75156700663c83a2", "mission": "62d2f0f6751567007abb199c", "rate": 10.0, "rarity": "uncommon", "rotation": "a", "id": "641269487d179f022214f592"}, {"type": "mission", "item": "641264a57d179f02190e41f3", "location": "62d2eb5d75156700663c83eb", "mission": "62d2f0cb751567007abb198d", "rate": 6.67, "rarity": "rare", "rotation": "b", "id": "641269487d179f022214f593"}, {"type": "mission", "item": "641264a57d179f02190e41f3", "location": "62d2eb6d75156700663c842e", "mission": "62d2f0a2751567007abb198b", "rate": 1.84, "rarity": "ultra_rare", "rotation": "c", "id": "641269487d179f022214f594"}, {"type": "mission", "item": "641264a57d179f02190e41f3", "location": "62d2eb6375156700663c8405", "mission": "62d2f073751567007abb196f", "rate": 10.0, "rarity": "uncommon", "rotation": "a", "id": "641269487d179f022214f595"}, {"type": "mission", "item": "641264a57d179f02190e41f3", "location": "62d2eb6e75156700663c8431", "mission": "62d2f0cb751567007abb198d", "rate": 14.29, "rarity": "uncommon", "rotation": "b", "id": "641269487d179f022214f596"}, {"type": "mission", "item": "641264a57d179f02190e41f3", "location": "62d2eb6075156700663c83f8", "mission": "62d2f0f5751567007abb199b", "rate": 14.29, "rarity": "uncommon", "rotation": "b", "id": "641269487d179f022214f597"}, {"type": "mission", "item": "641264a57d179f02190e41f3", "location": "62d2f103751567007abb19ff", "mission": "62d2f0a2751567007abb198b", "rate": 6.25, "rarity": "rare", "rotation": "b", "event": true, "id": "641269487d179f022214f598"}, {"type": "mission", "item": "641264a57d179f02190e41f3", "location": "62d2f103751567007abb19ff", "mission": "62d2f0a2751567007abb198b", "rate": 11.06, "rarity": "uncommon", "rotation": "c", "event": true, "id": "641269487d179f022214f599"}, {"type": "mission", "item": "641264a57d179f02190e41f3", "location": "62d2eb5375156700663c83c0", "mission": "62d2f073751567007abb196f", "rate": 10.0, "rarity": "uncommon", "rotation": "a", "id": "641269487d179f022214f59a"}, {"type": "mission", "item": "641264a57d179f02190e41f3", "location": "62d2f0fb751567007abb19b1", "mission": "62d2f0f8751567007abb19a6", "rate": 3.22, "rarity": "rare", "rotation": "b", "event": true, "id": "641269487d179f022214f59b"}, {"type": "mission", "item": "641264a57d179f02190e41f3", "location": "62d2eb5d75156700663c83ea", "mission": "62d2f0cb751567007abb198d", "rate": 6.67, "rarity": "rare", "rotation": "b", "id": "641269487d179f022214f59c"}, {"type": "mission", "item": "641264a57d179f02190e41f3", "location": "62d2eb5f75156700663c83f3", "mission": "62d2f0f8751567007abb19a6", "rate": 3.22, "rarity": "rare", "rotation": "b", "id": "641269487d179f022214f59d"}, {"type": "mission", "item": "641264a57d179f02190e41f3", "location": "62d2eb4d75156700663c83a8", "mission": "62d2f0a2751567007abb198b", "rate": 10.0, "rarity": "uncommon", "rotation": "a", "id": "641269487d179f022214f59e"}, {"type": "mission", "item": "641264a57d179f02190e41f3", "location": "62d2f102751567007abb19f2", "mission": "62d2f0cb751567007abb198d", "rate": 6.67, "rarity": "rare", "rotation": "b", "event": true, "id": "641269487d179f022214f59f"}, {"type": "mission", "item": "641264a57d179f02190e41f3", "location": "62d2f101751567007abb19e7", "mission": "62d2f0cb751567007abb198d", "rate": 6.67, "rarity": "rare", "rotation": "b", "event": true, "id": "641269487d179f022214f5a0"}, {"type": "mission", "item": "641264a57d179f02190e41f3", "location": "62d2eb5075156700663c83b4", "mission": "62d2f0cb751567007abb198d", "rate": 6.67, "rarity": "rare", "rotation": "b", "id": "641269487d179f022214f5a1"}, {"type": "mission", "item": "641264a57d179f02190e41f3", "location": "62d2eb6c75156700663c842a", "mission": "62d2f0a2751567007abb198b", "rate": 1.84, "rarity": "ultra_rare", "rotation": "c", "id": "641269487d179f022214f5a2"}, {"type": "mission", "item": "641264a57d179f02190e41f3", "location": "62d2f104751567007abb1a0a", "mission": "62d2f099751567007abb197d", "rate": 11.06, "rarity": "uncommon", "rotation": "c", "event": true, "id": "641269487d179f022214f5a3"}, {"type": "mission", "item": "641264a57d179f02190e41f3", "location": "62d2eb4875156700663c8393", "mission": "62d2f099751567007abb197d", "rate": 11.06, "rarity": "uncommon", "rotation": "c", "id": "641269487d179f022214f5a4"}, {"type": "mission", "item": "641264a57d179f02190e41f3", "location": "62d2eb5175156700663c83b9", "mission": "62d2f073751567007abb196f", "rate": 7.14, "rarity": "rare", "rotation": "b", "id": "641269487d179f022214f5a5"}, {"type": "mission", "item": "641264a57d179f02190e41f3", "location": "62d2eb5175156700663c83b9", "mission": "62d2f073751567007abb196f", "rate": 14.29, "rarity": "uncommon", "rotation": "c", "id": "641269487d179f022214f5a6"}, {"type": "mission", "item": "641264a57d179f02190e41f3", "location": "62d2eb3975156700663c835a", "mission": "62d2f0a2751567007abb198b", "rate": 6.25, "rarity": "rare", "rotation": "b", "id": "641269487d179f022214f5a7"}, {"type": "mission", "item": "641264a57d179f02190e41f3", "location": "62d2eb3975156700663c835a", "mission": "62d2f0a2751567007abb198b", "rate": 11.06, "rarity": "uncommon", "rotation": "c", "id": "641269487d179f022214f5a8"}, {"type": "mission", "item": "641264a57d179f02190e41f3", "location": "62d2f102751567007abb19f5", "mission": "62d2f0cb751567007abb198d", "rate": 11.06, "rarity": "uncommon", "rotation": "c", "event": true, "id": "641269487d179f022214f5a9"}, {"type": "mission", "item": "641264a57d179f02190e41f3", "location": "62d2eb5075156700663c83b6", "mission": "62d2f0a2751567007abb198b", "rate": 1.84, "rarity": "ultra_rare", "rotation": "c", "id": "641269487d179f022214f5aa"}, {"type": "mission", "item": "641264a57d179f02190e41f3", "location": "62d2f102751567007abb19f8", "mission": "62d2f099751567007abb197d", "rate": 6.67, "rarity": "rare", "rotation": "b", "event": true, "id": "641269487d179f022214f5ab"}, {"type": "mission", "item": "641264a57d179f02190e41f3", "location": "62d2eb6875156700663c8418", "mission": "62d2f099751567007abb197d", "rate": 6.67, "rarity": "rare", "rotation": "b", "id": "641269487d179f022214f5ac"}, {"type": "mission", "item": "641264a57d179f02190e41f3", "location": "62d2eb3f75156700663c836d", "mission": "62d2f0cb751567007abb198d", "rate": 2.05, "rarity": "rare", "rotation": "b", "id": "641269487d179f022214f5ad"}, {"type": "mission", "item": "641264a57d179f02190e41f3", "location": "62d2eb3f75156700663c836d", "mission": "62d2f0cb751567007abb198d", "rate": 6.49, "rarity": "rare", "rotation": "c", "id": "641269487d179f022214f5ae"}, {"type": "mission", "item": "641264a57d179f02190e41f3", "location": "62d2eb5e75156700663c83f1", "mission": "62d2f063751567007abb1961", "rate": 6.67, "rarity": "rare", "id": "641269487d179f022214f5af"}, {"type": "mission", "item": "641264a57d179f02190e41f3", "location": "62d2eb6f75156700663c8439", "mission": "62d2f097751567007abb1975", "rate": 6.67, "rarity": "rare", "id": "641269487d179f022214f5b0"}, {"type": "mission", "item": "641264a57d179f02190e41f3", "location": "62d2eb6b75156700663c8426", "mission": "62d2f0a2751567007abb198b", "rate": 6.96, "rarity": "rare", "rotation": "a", "id": "641269487d179f022214f5b1"}, {"type": "mission", "item": "641264a57d179f02190e41f3", "location": "62d2eb6b75156700663c8426", "mission": "62d2f0a2751567007abb198b", "rate": 9.09, "rarity": "rare", "rotation": "b", "id": "641269487d179f022214f5b2"}, {"type": "mission", "item": "641264a57d179f02190e41f3", "location": "62d2eb6b75156700663c8426", "mission": "62d2f0a2751567007abb198b", "rate": 9.68, "rarity": "rare", "rotation": "c", "id": "641269487d179f022214f5b3"}, {"type": "mission", "item": "641264a57d179f02190e41f3", "location": "62d2eb6f75156700663c8437", "mission": "62d2f0cb751567007abb198d", "rate": 9.09, "rarity": "rare", "rotation": "a", "id": "641269487d179f022214f5b4"}, {"type": "mission", "item": "641264a57d179f02190e41f3", "location": "62d2eb6f75156700663c8437", "mission": "62d2f0cb751567007abb198d", "rate": 12.5, "rarity": "uncommon", "rotation": "b", "id": "641269487d179f022214f5b5"}, {"type": "mission", "item": "641264a57d179f02190e41f3", "location": "62d2eb4675156700663c838c", "mission": "62d2f09b751567007abb1987", "rate": 6.25, "rarity": "rare", "id": "641269487d179f022214f5b6"}, {"type": "mission", "item": "641264a57d179f02190e41f3", "location": "62d2eb4775156700663c8390", "mission": "62d2f0f3751567007abb1991", "rate": 6.25, "rarity": "rare", "id": "641269487d179f022214f5b7"}, {"type": "mission", "item": "641264a57d179f02190e41f3", "location": "62d2eb3975156700663c8359", "mission": "62d2f073751567007abb196f", "rate": 9.09, "rarity": "rare", "rotation": "a", "id": "641269487d179f022214f5b8"}, {"type": "mission", "item": "641264a57d179f02190e41f3", "location": "62d2eb3975156700663c8359", "mission": "62d2f073751567007abb196f", "rate": 12.5, "rarity": "uncommon", "rotation": "b", "id": "641269487d179f022214f5b9"}, {"type": "mission", "item": "641264a57d179f02190e41f3", "location": "62d2f104751567007abb1a04", "mission": "62d2f097751567007abb1976", "rate": 2.01, "rarity": "rare", "rotation": "c", "event": true, "id": "641269487d179f022214f5ba"}, {"type": "mission", "item": "641264a57d179f02190e41f3", "location": "62d2eb7175156700663c843f", "mission": "62d2f0cb751567007abb198d", "rate": 11.06, "rarity": "uncommon", "rotation": "c", "id": "641269487d179f022214f5bb"}, {"type": "mission", "item": "641264a57d179f02190e41f3", "location": "62d2eb5375156700663c83c3", "mission": "62d2f0cb751567007abb198d", "rate": 12.5, "rarity": "uncommon", "rotation": "b", "id": "641269487d179f022214f5bc"}, {"type": "mission", "item": "641264a57d179f02190e41f3", "location": "62d2eb5475156700663c83c7", "mission": "62d2f0cb751567007abb198d", "rate": 6.67, "rarity": "rare", "rotation": "b", "id": "641269487d179f022214f5bd"}, {"type": "mission", "item": "641264a57d179f02190e41f3", "location": "62d2eb3d75156700663c8368", "mission": "62d2f0a2751567007abb198b", "rate": 10.0, "rarity": "uncommon", "rotation": "a", "id": "641269487d179f022214f5be"}, {"type": "mission", "item": "641264a57d179f02190e41f3", "location": "62d2eb5b75156700663c83e2", "mission": "62d2f0f5751567007abb199b", "rate": 14.29, "rarity": "uncommon", "rotation": "a", "id": "641269487d179f022214f5bf"}, {"type": "mission", "item": "641264a57d179f02190e41f3", "location": "63887510e7c98800de87fdd1", "mission": "62d2f0cb751567007abb198d", "rate": 10.0, "rarity": "uncommon", "rotation": "b", "id": "641269487d179f022214f5c0"}, {"type": "mission", "item": "641264a57d179f02190e41f3", "location": "63887511e7c98800de87fdd2", "mission": "62d2f0cb751567007abb198d", "rate": 4.76, "rarity": "rare", "rotation": "b", "id": "641269487d179f022214f5c1"}, {"type": "mission", "item": "641264a57d179f02190e41f3", "location": "62d2eb6e75156700663c8432", "mission": "62d2f0a2751567007abb198b", "rate": 10.0, "rarity": "uncommon", "rotation": "a", "id": "641269487d179f022214f5c2"}, {"type": "mission", "item": "641264a57d179f02190e41f3", "location": "62d2eb3b75156700663c835f", "mission": "62d2f0cb751567007abb198d", "rate": 6.67, "rarity": "rare", "rotation": "b", "id": "641269487d179f022214f5c3"}, {"type": "mission", "item": "641264a57d179f02190e41f3", "location": "62d2eb4a75156700663c839e", "mission": "62d2f0f8751567007abb19a6", "rate": 3.22, "rarity": "rare", "rotation": "c", "id": "641269487d179f022214f5c4"}, {"type": "mission", "item": "641264a57d179f02190e41f3", "location": "62d2f104751567007abb1a07", "mission": "62d2f099751567007abb1981", "rate": 9.68, "rarity": "rare", "rotation": "c", "id": "641269487d179f022214f5c5"}, {"type": "mission", "item": "641264a57d179f02190e41f3", "location": "62d2eb6e75156700663c8436", "mission": "62d2f07a751567007abb1970", "rate": 2.0, "rarity": "rare", "id": "641269487d179f022214f5c6"}, {"type": "mission", "item": "641264a57d179f02190e41f3", "location": "62d2eb6e75156700663c8436", "mission": "62d2f05d751567007abb195c", "rate": 4.8, "rarity": "rare", "rotation": "a", "id": "641269487d179f022214f5c7"}, {"type": "mission", "item": "641264a57d179f02190e41f3", "location": "62d2eb5e75156700663c83f0", "mission": "62d2f07a751567007abb1970", "rate": 2.0, "rarity": "rare", "id": "641269487d179f022214f5c8"}, {"type": "mission", "item": "641264a57d179f02190e41f3", "location": "62d2eb5e75156700663c83f0", "mission": "62d2f05d751567007abb195c", "rate": 4.8, "rarity": "rare", "rotation": "a", "id": "641269487d179f022214f5c9"}, {"type": "mission", "item": "641264a57d179f02190e41f3", "location": "62d2eb4275156700663c837d", "mission": "62d2f07a751567007abb1970", "rate": 2.0, "rarity": "rare", "id": "641269487d179f022214f5ca"}, {"type": "mission", "item": "641264a57d179f02190e41f3", "location": "62d2eb4275156700663c837d", "mission": "62d2f05d751567007abb195c", "rate": 4.8, "rarity": "rare", "rotation": "a", "id": "641269487d179f022214f5cb"}, {"type": "mission", "item": "641264a57d179f02190e41f3", "location": "62d2eb4a75156700663c839b", "mission": "62d2f07a751567007abb1970", "rate": 2.0, "rarity": "rare", "id": "641269487d179f022214f5cc"}, {"type": "mission", "item": "641264a57d179f02190e41f3", "location": "62d2eb4a75156700663c839b", "mission": "62d2f05d751567007abb195c", "rate": 4.8, "rarity": "rare", "rotation": "a", "id": "641269487d179f022214f5cd"}, {"type": "mission", "item": "641264a57d179f02190e41f3", "location": "62d2eb6d75156700663c842c", "mission": "62d2f05d751567007abb195c", "rate": 4.35, "rarity": "rare", "rotation": "a", "id": "641269487d179f022214f5ce"}, {"type": "mission", "item": "641264a57d179f02190e41f3", "location": "62d2eb6075156700663c83fb", "mission": "62d2f05d751567007abb195c", "rate": 4.35, "rarity": "rare", "rotation": "a", "id": "641269487d179f022214f5cf"}, {"type": "mission", "item": "641264a57d179f02190e41f3", "location": "62d2eb6f75156700663c8438", "mission": "62d2f05d751567007abb195c", "rate": 4.35, "rarity": "rare", "rotation": "a", "id": "641269487d179f022214f5d0"}, {"type": "mission", "item": "641264a57d179f02190e41f3", "location": "62d2eb5175156700663c83ba", "mission": "62d2f05d751567007abb195c", "rate": 4.35, "rarity": "rare", "rotation": "a", "id": "641269487d179f022214f5d1"}, {"type": "mission", "item": "641264a57d179f02190e41f3", "location": "62d2eb6e75156700663c8433", "mission": "62d2f05d751567007abb195c", "rate": 4.35, "rarity": "rare", "rotation": "a", "id": "641269487d179f022214f5d2"}, {"type": "mission", "item": "641264a57d179f02190e41f3", "location": "62d2eb6975156700663c841c", "mission": "62d2f05d751567007abb195c", "rate": 4.35, "rarity": "rare", "rotation": "a", "id": "641269487d179f022214f5d3"}, {"type": "mission", "item": "641264a57d179f02190e41f3", "location": "62d2eb4075156700663c8374", "mission": "62d2f065751567007abb1967", "rate": 3.33, "rarity": "rare", "rotation": "b", "id": "641269487d179f022214f5d4"}, {"type": "mission", "item": "641264a57d179f02190e41f3", "location": "62d2eb6075156700663c83fa", "mission": "62d2f099751567007abb1982", "rate": 3.33, "rarity": "rare", "rotation": "b", "id": "641269487d179f022214f5d5"}, {"type": "mission", "item": "641264a57d179f02190e41f3", "location": "62d2eb3c75156700663c8364", "mission": "62d2f0f4751567007abb1997", "rate": 3.33, "rarity": "rare", "rotation": "b", "id": "641269487d179f022214f5d6"}, {"type": "mission", "item": "641264a57d179f02190e41f3", "location": "62d2eb3d75156700663c8367", "mission": "62d2f0f9751567007abb19a9", "rate": 13.57, "rarity": "uncommon", "rotation": "a", "stage": ["4"], "id": "641269487d179f022214f5d8"}, {"type": "mission", "item": "641264a57d179f02190e41f3", "location": "62d2eb3d75156700663c8367", "mission": "62d2f0f9751567007abb19a9", "rate": 17.92, "rarity": "uncommon", "rotation": "a", "stage": ["final"], "id": "641269487d179f022214f5d9"}, {"type": "mission", "item": "641264a57d179f02190e41f3", "location": "62d2eb3d75156700663c8367", "mission": "62d2f0f9751567007abb19a7", "rate": 1.14, "rarity": "ultra_rare", "rotation": "a", "stage": ["1"], "id": "641269487d179f022214f5da"}, {"type": "mission", "item": "641264a57d179f02190e41f3", "location": "62d2eb3d75156700663c8367", "mission": "62d2f0f9751567007abb19a7", "rate": 0.42, "rarity": "legendary", "rotation": "a", "stage": ["4"], "id": "641269487d179f022214f5dc"}, {"type": "mission", "item": "641264a57d179f02190e41f3", "location": "62d2eb3d75156700663c8367", "mission": "62d2f0f9751567007abb19a7", "rate": 0.67, "rarity": "legendary", "rotation": "a", "stage": ["final"], "id": "641269487d179f022214f5dd"}, {"type": "mission", "item": "641264a57d179f02190e41f3", "location": "62d2eb3a75156700663c835c", "mission": "62d2f0fa751567007abb19aa", "rate": 1.88, "rarity": "ultra_rare", "rotation": "a", "stage": ["final"], "id": "641269487d179f022214f5de"}, {"type": "mission", "item": "641264a57d179f02190e41f3", "location": "62d2eb3a75156700663c835c", "mission": "62d2f0fa751567007abb19aa", "rate": 3.75, "rarity": "rare", "rotation": "b", "stage": ["final"], "id": "641269487d179f022214f5df"}, {"type": "mission", "item": "641264a57d179f02190e41f3", "location": "62d2eb3a75156700663c835c", "mission": "62d2f065751567007abb1965", "rate": 0.5, "rarity": "legendary", "rotation": "a", "stage": ["final"], "id": "641269487d179f022214f5e0"}, {"type": "mission", "item": "641264a57d179f02190e41f3", "location": "62d2eb3a75156700663c835c", "mission": "62d2f0f6751567007abb199e", "rate": 1.88, "rarity": "ultra_rare", "rotation": "c", "stage": ["final"], "id": "641269487d179f022214f5e1"}, {"type": "mission", "item": "641264a57d179f02190e41f3", "location": "62d2eb3a75156700663c835c", "mission": "62d2f09a751567007abb1985", "rate": 1.88, "rarity": "ultra_rare", "rotation": "a", "stage": ["4"], "id": "641269487d179f022214f5e3"}, {"type": "mission", "item": "641264a57d179f02190e41f3", "location": "62d2eb3a75156700663c835c", "mission": "62d2f09a751567007abb1985", "rate": 3.75, "rarity": "rare", "rotation": "a", "stage": ["final"], "id": "641269487d179f022214f5e4"}, {"type": "mission", "item": "641264a57d179f02190e41f3", "location": "62d2eb3a75156700663c835c", "mission": "62d2f09a751567007abb1985", "rate": 3.75, "rarity": "rare", "rotation": "b", "stage": ["4"], "id": "641269487d179f022214f5e6"}, {"type": "mission", "item": "641264a57d179f02190e41f3", "location": "62d2eb3a75156700663c835c", "mission": "62d2f09a751567007abb1985", "rate": 7.5, "rarity": "rare", "rotation": "b", "stage": ["final"], "id": "641269487d179f022214f5e7"}, {"type": "mission", "item": "641264a57d179f02190e41f3", "location": "62d2eb3a75156700663c835c", "mission": "62d2f071751567007abb196a", "rate": 0.5, "rarity": "legendary", "rotation": "a", "stage": ["4"], "id": "641269487d179f022214f5e8"}, {"type": "mission", "item": "641264a57d179f02190e41f3", "location": "62d2eb3a75156700663c835c", "mission": "62d2f071751567007abb196a", "rate": 1.0, "rarity": "ultra_rare", "rotation": "a", "stage": ["final"], "id": "641269487d179f022214f5e9"}, {"type": "mission", "item": "641264a57d179f02190e41f3", "location": "62d2eb3a75156700663c835c", "mission": "62d2f0f6751567007abb199d", "rate": 1.88, "rarity": "ultra_rare", "rotation": "c", "stage": ["4"], "id": "641269487d179f022214f5eb"}, {"type": "mission", "item": "641264a57d179f02190e41f3", "location": "62d2eb3a75156700663c835c", "mission": "62d2f0f6751567007abb199d", "rate": 3.75, "rarity": "rare", "rotation": "c", "stage": ["final"], "id": "641269487d179f022214f5ec"}, {"type": "mission", "item": "641264a57d179f02190e41f3", "mission": "62d2f097751567007abb1974", "rate": 2.01, "rarity": "rare", "rotation": "c", "id": "641269487d179f022214f5ed"}, {"type": "mission", "item": "641264a57d179f02190e41f3", "mission": "62d2f099751567007abb197e", "rate": 2.01, "rarity": "rare", "rotation": "c", "id": "641269487d179f022214f5ee"}, {"type": "mission", "item": "641264a57d179f02190e41f3", "mission": "62d2f0a2751567007abb1989", "rate": 2.01, "rarity": "rare", "rotation": "c", "id": "641269487d179f022214f5ef"}, {"type": "mission", "item": "641264a57d179f02190e41f3", "mission": "62d2f098751567007abb197a", "rate": 2.01, "rarity": "rare", "rotation": "c", "id": "641269487d179f022214f5f0"}, {"type": "mission", "item": "641264a57d179f02190e41f3", "mission": "62d2f07e751567007abb1972", "rate": 2.01, "rarity": "rare", "rotation": "c", "id": "641269487d179f022214f5f1"}, {"type": "mission", "item": "641264a57d179f02190e41f3", "mission": "62d2f049751567007abb1955", "rate": 2.01, "rarity": "rare", "rotation": "c", "id": "641269487d179f022214f5f2"}, {"type": "mission", "item": "641264a57d179f02190e41f3", "mission": "62d2f0a2751567007abb198a", "rate": 2.01, "rarity": "rare", "rotation": "c", "id": "641269487d179f022214f5f3"}, {"type": "mission", "item": "641264a57d179f02190e41f3", "mission": "62d2f0f4751567007abb1998", "rate": 2.01, "rarity": "rare", "rotation": "c", "id": "641269487d179f022214f5f4"}, {"type": "npc", "item": "641264a57d179f02190e41f3", "npc": "62d2f014751567007abb1790", "rate": 0.75, "rarity": "rare", "id": "641269487d179f022214f5f5"}, {"type": "mission", "item": "641264a57d179f02190e41f3", "location": "62d2eb3d75156700663c8367", "mission": "62d2f0f9751567007abb19a9", "rate": 18.45, "rarity": "uncommon", "rotation": "a", "stage": ["2", "3"], "id": "644b04e97ec19000567fa44f"}, {"type": "mission", "item": "641264a57d179f02190e41f3", "location": "62d2eb3d75156700663c8367", "mission": "62d2f0f9751567007abb19a7", "rate": 0.58, "rarity": "legendary", "rotation": "a", "stage": ["2", "3"], "id": "644b04e97ec19000567fa450"}, {"type": "mission", "item": "641264a57d179f02190e41f3", "location": "62d2eb3a75156700663c835c", "mission": "62d2f09a751567007abb1985", "rate": 2.34, "rarity": "rare", "rotation": "a", "stage": ["2", "3"], "id": "644b04e97ec19000567fa451"}, {"type": "mission", "item": "641264a57d179f02190e41f3", "location": "62d2eb3a75156700663c835c", "mission": "62d2f09a751567007abb1985", "rate": 4.69, "rarity": "rare", "rotation": "b", "stage": ["2", "3"], "id": "644b04e97ec19000567fa452"}, {"type": "mission", "item": "641264a57d179f02190e41f3", "location": "62d2eb3a75156700663c835c", "mission": "62d2f0f6751567007abb199d", "rate": 2.34, "rarity": "rare", "rotation": "c", "stage": ["2", "3"], "id": "644b04e97ec19000567fa453"}]}}