{"payload": {"dropsources": [{"type": "npc", "item": "580e38faca550948410af0a7", "npc": "62d2f033751567007abb1889", "rate": 1.25, "rarity": "uncommon", "id": "62d3525c650ea601a7ad2473"}, {"type": "npc", "item": "580e38faca550948410af0a7", "npc": "62d2eff5751567007abb168a", "rate": 1.25, "rarity": "uncommon", "id": "62d3525c650ea601a7ad2474"}, {"type": "npc", "item": "580e38faca550948410af0a7", "npc": "62d2f02d751567007abb1857", "rate": 1.25, "rarity": "uncommon", "id": "62d3525c650ea601a7ad2475"}, {"type": "npc", "item": "580e38faca550948410af0a7", "npc": "62d2f033751567007abb188e", "rate": 1.25, "rarity": "uncommon", "id": "62d3525c650ea601a7ad2476"}, {"type": "npc", "item": "580e38faca550948410af0a7", "npc": "62d2f005751567007abb1718", "rate": 1.25, "rarity": "uncommon", "id": "62d3525c650ea601a7ad2477"}, {"type": "npc", "item": "580e38faca550948410af0a7", "npc": "62d2f016751567007abb17ad", "rate": 1.25, "rarity": "uncommon", "id": "62d3525c650ea601a7ad2478"}, {"type": "npc", "item": "580e38faca550948410af0a7", "npc": "62d2f00a751567007abb1743", "rate": 1.25, "rarity": "uncommon", "id": "62d3525c650ea601a7ad2479"}, {"type": "npc", "item": "580e38faca550948410af0a7", "npc": "62d2eff9751567007abb16b4", "rate": 1.25, "rarity": "uncommon", "id": "62d3525c650ea601a7ad247a"}, {"type": "npc", "item": "580e38faca550948410af0a7", "npc": "62d2f026751567007abb181d", "rate": 1.25, "rarity": "uncommon", "id": "62d3525c650ea601a7ad247b"}, {"type": "npc", "item": "580e38faca550948410af0a7", "npc": "62d2f00a751567007abb173e", "rate": 1.25, "rarity": "uncommon", "id": "62d3525c650ea601a7ad247c"}, {"type": "npc", "item": "580e38faca550948410af0a7", "npc": "62d2effa751567007abb16be", "rate": 1.25, "rarity": "uncommon", "id": "62d3525c650ea601a7ad247d"}, {"type": "npc", "item": "580e38faca550948410af0a7", "npc": "62d2f029751567007abb1840", "rate": 1.25, "rarity": "uncommon", "id": "62d3525c650ea601a7ad247e"}, {"type": "npc", "item": "580e38faca550948410af0a7", "npc": "62d2f007751567007abb1725", "rate": 1.25, "rarity": "uncommon", "id": "62d3525c650ea601a7ad247f"}, {"type": "npc", "item": "580e38faca550948410af0a7", "npc": "62d2f02f751567007abb186a", "rate": 1.25, "rarity": "uncommon", "id": "62d3525c650ea601a7ad2480"}, {"type": "npc", "item": "580e38faca550948410af0a7", "npc": "62d2f043751567007abb1929", "rate": 1.25, "rarity": "uncommon", "id": "62d3525c650ea601a7ad2481"}, {"type": "npc", "item": "580e38faca550948410af0a7", "npc": "62d2f02c751567007abb1852", "rate": 1.25, "rarity": "uncommon", "id": "62d3525c650ea601a7ad2482"}]}}