{
    "payload": {
        "dropsources": [
            {
                "type": "npc",
                "item": "57c5948794b4b0f159ab5e0e",
                "npc": "62d2eff6751567007abb1696",
                "rate": 2.78,
                "rarity": "rare",
                "id": "62d3525e650ea601a7ad26e3"
            },
            {
                "type": "npc",
                "item": "57c5948794b4b0f159ab5e0e",
                "npc": "62d2f041751567007abb1916",
                "rate": 2.78,
                "rarity": "rare",
                "id": "62d3525e650ea601a7ad26e4"
            },
            {
                "type": "npc",
                "item": "57c5948794b4b0f159ab5e0e",
                "npc": "62d2efff751567007abb16ed",
                "rate": 0.03,
                "rarity": "ultra_rare",
                "id": "62d3525e650ea601a7ad26e6"
            },
            {
                "type": "npc",
                "item": "57c5948794b4b0f159ab5e0e",
                "npc": "62d2f034751567007abb1891",
                "rate": 0.03,
                "rarity": "ultra_rare",
                "id": "63f103ed07ebe90061f4bf1d"
            },
            {
                "type": "mission",
                "item": "57c5948794b4b0f159ab5e0e",
                "location": "644b01ab7ec190004dbb80c1",
                "mission": "644b00457ec1900044b97743",
                "rate": 1.49,
                "rarity": "ultra_rare",
                "modifier": "normal",
                "id": "644b04eb7ec19000567fa5c7"
            },
            {
                "type": "mission",
                "item": "57c5948794b4b0f159ab5e0e",
                "location": "644b01ab7ec190004dbb80c1",
                "mission": "644b00457ec1900044b97742",
                "rate": 1.03,
                "rarity": "ultra_rare",
                "modifier": "normal",
                "id": "644b04eb7ec19000567fa5c8"
            }
        ]
    }
}