{
    "payload": {
        "dropsources": [
            {
                "type": "mission",
                "item": "5fb84768c34da3004797d548",
                "location": "62d2eb3a75156700663c835c",
                "mission": "62d2f0f6751567007abb199e",
                "rate": 3.75,
                "rarity": "rare",
                "rotation": "b",
                "stage": [
                    "final"
                ],
                "id": "62d35259650ea601a7ad1fab"
            },
            {
                "type": "mission",
                "item": "5fb84768c34da3004797d548",
                "location": "62d2eb3a75156700663c835c",
                "mission": "62d2f0f6751567007abb199d",
                "rate": 3.75,
                "rarity": "rare",
                "rotation": "b",
                "stage": [
                    "4"
                ],
                "id": "62d35259650ea601a7ad1fad"
            },
            {
                "type": "mission",
                "item": "5fb84768c34da3004797d548",
                "location": "62d2eb3a75156700663c835c",
                "mission": "62d2f0f6751567007abb199d",
                "rate": 7.5,
                "rarity": "rare",
                "rotation": "b",
                "stage": [
                    "final"
                ],
                "id": "62d35259650ea601a7ad1fae"
            },
            {
                "type": "mission",
                "item": "5fb84768c34da3004797d548",
                "location": "62d2eb3a75156700663c835c",
                "mission": "62d2f0f6751567007abb199d",
                "rate": 4.69,
                "rarity": "rare",
                "rotation": "b",
                "stage": [
                    "2",
                    "3"
                ],
                "id": "644b04eb7ec19000567fa647"
            }
        ]
    }
}