{
    "payload": {
        "dropsources": [
            {
                "type": "mission",
                "item": "54a74454e779892d5e515677",
                "location": "62d2eb4475156700663c8384",
                "mission": "62d2f063751567007abb1961",
                "rate": 0.34,
                "rarity": "legendary",
                "id": "62d3524d650ea601a7ad07ff"
            },
            {
                "type": "mission",
                "item": "54a74454e779892d5e515677",
                "location": "62d2eb7375156700663c8447",
                "mission": "62d2f063751567007abb1961",
                "rate": 0.34,
                "rarity": "legendary",
                "id": "62d3524d650ea601a7ad0800"
            },
            {
                "type": "mission",
                "item": "54a74454e779892d5e515677",
                "location": "62d2eb4e75156700663c83ab",
                "mission": "62d2f063751567007abb1961",
                "rate": 0.34,
                "rarity": "legendary",
                "id": "62d3524d650ea601a7ad0801"
            },
            {
                "type": "mission",
                "item": "54a74454e779892d5e515677",
                "location": "62d2f0fe751567007abb19d1",
                "mission": "62d2f063751567007abb1961",
                "rate": 0.34,
                "rarity": "legendary",
                "event": true,
                "id": "62d3524d650ea601a7ad0803"
            },
            {
                "type": "mission",
                "item": "54a74454e779892d5e515677",
                "location": "62d2eb5275156700663c83bd",
                "mission": "62d2f063751567007abb1961",
                "rate": 0.34,
                "rarity": "legendary",
                "id": "62d3524d650ea601a7ad0805"
            },
            {
                "type": "mission",
                "item": "54a74454e779892d5e515677",
                "location": "62d2f101751567007abb19ee",
                "mission": "62d2f063751567007abb1961",
                "rate": 0.34,
                "rarity": "legendary",
                "event": true,
                "id": "62d3524d650ea601a7ad0807"
            },
            {
                "type": "mission",
                "item": "54a74454e779892d5e515677",
                "location": "62d2eb6e75156700663c8434",
                "mission": "62d2f063751567007abb1961",
                "rate": 0.34,
                "rarity": "legendary",
                "id": "62d3524d650ea601a7ad0808"
            },
            {
                "type": "mission",
                "item": "54a74454e779892d5e515677",
                "location": "62d2eb4675156700663c838b",
                "mission": "62d2f063751567007abb1961",
                "rate": 0.34,
                "rarity": "legendary",
                "id": "62d3524d650ea601a7ad0809"
            },
            {
                "type": "mission",
                "item": "54a74454e779892d5e515677",
                "location": "62d2eb4b75156700663c839f",
                "mission": "62d2f0cb751567007abb198d",
                "rate": 6.67,
                "rarity": "rare",
                "rotation": "b",
                "id": "62d3524d650ea601a7ad080b"
            },
            {
                "type": "mission",
                "item": "54a74454e779892d5e515677",
                "location": "62d2f105751567007abb1a10",
                "mission": "62d2f0cb751567007abb198d",
                "rate": 6.67,
                "rarity": "rare",
                "rotation": "b",
                "event": true,
                "id": "62d3524d650ea601a7ad080c"
            },
            {
                "type": "mission",
                "item": "54a74454e779892d5e515677",
                "location": "62d2eb5975156700663c83dc",
                "mission": "62d2f0f8751567007abb19a6",
                "rate": 7.04,
                "rarity": "rare",
                "rotation": "c",
                "id": "62d3524d650ea601a7ad080d"
            },
            {
                "type": "mission",
                "item": "54a74454e779892d5e515677",
                "location": "62d2f0fa751567007abb19ae",
                "mission": "62d2f063751567007abb1961",
                "rate": 0.34,
                "rarity": "legendary",
                "event": true,
                "id": "62d3524d650ea601a7ad0810"
            },
            {
                "type": "mission",
                "item": "54a74454e779892d5e515677",
                "location": "62d2eb5675156700663c83cd",
                "mission": "62d2f0cb751567007abb198d",
                "rate": 6.67,
                "rarity": "rare",
                "rotation": "b",
                "id": "62d3524d650ea601a7ad0811"
            },
            {
                "type": "mission",
                "item": "54a74454e779892d5e515677",
                "location": "62d2eb5c75156700663c83e9",
                "mission": "62d2f063751567007abb1961",
                "rate": 0.34,
                "rarity": "legendary",
                "id": "62d3524d650ea601a7ad0812"
            },
            {
                "type": "mission",
                "item": "54a74454e779892d5e515677",
                "location": "62d2eb5475156700663c83c6",
                "mission": "62d2f099751567007abb197d",
                "rate": 6.67,
                "rarity": "rare",
                "rotation": "b",
                "id": "62d3524d650ea601a7ad0814"
            },
            {
                "type": "mission",
                "item": "54a74454e779892d5e515677",
                "location": "62d2eb4175156700663c8376",
                "mission": "62d2f0f8751567007abb19a6",
                "rate": 7.04,
                "rarity": "rare",
                "rotation": "c",
                "id": "62d3524d650ea601a7ad0815"
            },
            {
                "type": "mission",
                "item": "54a74454e779892d5e515677",
                "location": "62d2eb4b75156700663c83a0",
                "mission": "62d2f0cb751567007abb198d",
                "rate": 6.67,
                "rarity": "rare",
                "rotation": "b",
                "id": "62d3524d650ea601a7ad0816"
            },
            {
                "type": "mission",
                "item": "54a74454e779892d5e515677",
                "location": "62d2eb6875156700663c841a",
                "mission": "62d2f063751567007abb1961",
                "rate": 0.34,
                "rarity": "legendary",
                "id": "62d3524d650ea601a7ad0818"
            },
            {
                "type": "mission",
                "item": "54a74454e779892d5e515677",
                "location": "62d2eb4d75156700663c83aa",
                "mission": "62d2f0cb751567007abb198d",
                "rate": 6.67,
                "rarity": "rare",
                "rotation": "b",
                "id": "62d3524d650ea601a7ad0819"
            },
            {
                "type": "mission",
                "item": "54a74454e779892d5e515677",
                "location": "62d2eb7175156700663c8441",
                "mission": "62d2f0f8751567007abb19a6",
                "rate": 7.04,
                "rarity": "rare",
                "rotation": "c",
                "id": "62d3524d650ea601a7ad081a"
            },
            {
                "type": "mission",
                "item": "54a74454e779892d5e515677",
                "location": "62d2eb3e75156700663c836b",
                "mission": "62d2f099751567007abb197d",
                "rate": 6.67,
                "rarity": "rare",
                "rotation": "b",
                "id": "62d3524d650ea601a7ad081b"
            },
            {
                "type": "mission",
                "item": "54a74454e779892d5e515677",
                "location": "62d2f100751567007abb19e4",
                "mission": "62d2f063751567007abb1961",
                "rate": 0.34,
                "rarity": "legendary",
                "event": true,
                "id": "62d3524d650ea601a7ad081c"
            },
            {
                "type": "mission",
                "item": "54a74454e779892d5e515677",
                "location": "62d2eb6975156700663c841e",
                "mission": "62d2f063751567007abb1961",
                "rate": 0.34,
                "rarity": "legendary",
                "id": "62d3524d650ea601a7ad081d"
            },
            {
                "type": "mission",
                "item": "54a74454e779892d5e515677",
                "location": "62d2f0fb751567007abb19b3",
                "mission": "62d2f0f8751567007abb19a6",
                "rate": 7.04,
                "rarity": "rare",
                "rotation": "c",
                "event": true,
                "id": "62d3524d650ea601a7ad081e"
            },
            {
                "type": "mission",
                "item": "54a74454e779892d5e515677",
                "location": "62d2f0fd751567007abb19c2",
                "mission": "62d2f063751567007abb1961",
                "rate": 0.34,
                "rarity": "legendary",
                "event": true,
                "id": "62d3524d650ea601a7ad081f"
            },
            {
                "type": "mission",
                "item": "54a74454e779892d5e515677",
                "location": "62d2f100751567007abb19e1",
                "mission": "62d2f0cb751567007abb198d",
                "rate": 6.67,
                "rarity": "rare",
                "rotation": "b",
                "event": true,
                "id": "62d3524d650ea601a7ad0821"
            },
            {
                "type": "mission",
                "item": "54a74454e779892d5e515677",
                "location": "62d2eb4d75156700663c83a7",
                "mission": "62d2f063751567007abb1961",
                "rate": 0.34,
                "rarity": "legendary",
                "id": "62d3524d650ea601a7ad0822"
            },
            {
                "type": "mission",
                "item": "54a74454e779892d5e515677",
                "location": "62d2f0fc751567007abb19b8",
                "mission": "62d2f0f8751567007abb19a6",
                "rate": 7.04,
                "rarity": "rare",
                "rotation": "c",
                "event": true,
                "id": "62d3524d650ea601a7ad0823"
            },
            {
                "type": "mission",
                "item": "54a74454e779892d5e515677",
                "location": "62d2eb4b75156700663c83a2",
                "mission": "62d2f0f6751567007abb199c",
                "rate": 14.29,
                "rarity": "uncommon",
                "rotation": "c",
                "id": "62d3524d650ea601a7ad0825"
            },
            {
                "type": "mission",
                "item": "54a74454e779892d5e515677",
                "location": "62d2eb5d75156700663c83eb",
                "mission": "62d2f0cb751567007abb198d",
                "rate": 6.67,
                "rarity": "rare",
                "rotation": "b",
                "id": "62d3524d650ea601a7ad0826"
            },
            {
                "type": "mission",
                "item": "54a74454e779892d5e515677",
                "location": "62d2f0fb751567007abb19b1",
                "mission": "62d2f0f8751567007abb19a6",
                "rate": 7.04,
                "rarity": "rare",
                "rotation": "c",
                "event": true,
                "id": "62d3524d650ea601a7ad0828"
            },
            {
                "type": "mission",
                "item": "54a74454e779892d5e515677",
                "location": "62d2eb5d75156700663c83ea",
                "mission": "62d2f0cb751567007abb198d",
                "rate": 6.67,
                "rarity": "rare",
                "rotation": "b",
                "id": "62d3524d650ea601a7ad0829"
            },
            {
                "type": "mission",
                "item": "54a74454e779892d5e515677",
                "location": "62d2eb5f75156700663c83f3",
                "mission": "62d2f0f8751567007abb19a6",
                "rate": 7.04,
                "rarity": "rare",
                "rotation": "c",
                "id": "62d3524d650ea601a7ad082a"
            },
            {
                "type": "mission",
                "item": "54a74454e779892d5e515677",
                "location": "62d2f102751567007abb19f2",
                "mission": "62d2f0cb751567007abb198d",
                "rate": 6.67,
                "rarity": "rare",
                "rotation": "b",
                "event": true,
                "id": "62d3524d650ea601a7ad082c"
            },
            {
                "type": "mission",
                "item": "54a74454e779892d5e515677",
                "location": "62d2f101751567007abb19e7",
                "mission": "62d2f0cb751567007abb198d",
                "rate": 6.67,
                "rarity": "rare",
                "rotation": "b",
                "event": true,
                "id": "62d3524d650ea601a7ad082d"
            },
            {
                "type": "mission",
                "item": "54a74454e779892d5e515677",
                "location": "62d2eb5075156700663c83b4",
                "mission": "62d2f0cb751567007abb198d",
                "rate": 6.67,
                "rarity": "rare",
                "rotation": "b",
                "id": "62d3524d650ea601a7ad082e"
            },
            {
                "type": "mission",
                "item": "54a74454e779892d5e515677",
                "location": "62d2eb5875156700663c83d6",
                "mission": "62d2f063751567007abb1961",
                "rate": 0.34,
                "rarity": "legendary",
                "id": "62d3524d650ea601a7ad082f"
            },
            {
                "type": "mission",
                "item": "54a74454e779892d5e515677",
                "location": "62d2f102751567007abb19f8",
                "mission": "62d2f063751567007abb1961",
                "rate": 0.34,
                "rarity": "legendary",
                "event": true,
                "id": "62d3524d650ea601a7ad0831"
            },
            {
                "type": "mission",
                "item": "54a74454e779892d5e515677",
                "location": "62d2f0fa751567007abb19ad",
                "mission": "62d2f063751567007abb1961",
                "rate": 0.34,
                "rarity": "legendary",
                "event": true,
                "id": "62d3524d650ea601a7ad0832"
            },
            {
                "type": "mission",
                "item": "54a74454e779892d5e515677",
                "location": "62d2f102751567007abb19f8",
                "mission": "62d2f099751567007abb197d",
                "rate": 6.67,
                "rarity": "rare",
                "rotation": "b",
                "event": true,
                "id": "62d3524d650ea601a7ad0833"
            },
            {
                "type": "mission",
                "item": "54a74454e779892d5e515677",
                "location": "62d2eb6875156700663c8418",
                "mission": "62d2f099751567007abb197d",
                "rate": 6.67,
                "rarity": "rare",
                "rotation": "b",
                "id": "62d3524d650ea601a7ad0834"
            },
            {
                "type": "mission",
                "item": "54a74454e779892d5e515677",
                "location": "62d2f100751567007abb19df",
                "mission": "62d2f063751567007abb1961",
                "rate": 0.34,
                "rarity": "legendary",
                "event": true,
                "id": "62d3524d650ea601a7ad0835"
            },
            {
                "type": "mission",
                "item": "54a74454e779892d5e515677",
                "location": "62d2eb6475156700663c840a",
                "mission": "62d2f063751567007abb1961",
                "rate": 0.34,
                "rarity": "legendary",
                "id": "62d3524d650ea601a7ad0836"
            },
            {
                "type": "mission",
                "item": "54a74454e779892d5e515677",
                "location": "62d2f0ff751567007abb19d8",
                "mission": "62d2f063751567007abb1961",
                "rate": 0.34,
                "rarity": "legendary",
                "event": true,
                "id": "62d3524d650ea601a7ad0837"
            },
            {
                "type": "mission",
                "item": "54a74454e779892d5e515677",
                "location": "62d2f104751567007abb1a04",
                "mission": "62d2f097751567007abb1976",
                "rate": 2.01,
                "rarity": "rare",
                "rotation": "c",
                "event": true,
                "id": "62d3524d650ea601a7ad0838"
            },
            {
                "type": "mission",
                "item": "54a74454e779892d5e515677",
                "location": "62d2eb5475156700663c83c7",
                "mission": "62d2f0cb751567007abb198d",
                "rate": 6.67,
                "rarity": "rare",
                "rotation": "b",
                "id": "62d3524d650ea601a7ad0839"
            },
            {
                "type": "mission",
                "item": "54a74454e779892d5e515677",
                "location": "62d2eb6875156700663c8419",
                "mission": "62d2f063751567007abb1961",
                "rate": 0.34,
                "rarity": "legendary",
                "id": "62d3524d650ea601a7ad083b"
            },
            {
                "type": "mission",
                "item": "54a74454e779892d5e515677",
                "location": "62d2eb3b75156700663c835f",
                "mission": "62d2f0cb751567007abb198d",
                "rate": 6.67,
                "rarity": "rare",
                "rotation": "b",
                "id": "62d3524d650ea601a7ad083d"
            },
            {
                "type": "mission",
                "item": "54a74454e779892d5e515677",
                "location": "62d2eb4a75156700663c839e",
                "mission": "62d2f0f8751567007abb19a6",
                "rate": 13.33,
                "rarity": "uncommon",
                "rotation": "a",
                "id": "62d3524d650ea601a7ad083e"
            },
            {
                "type": "mission",
                "item": "54a74454e779892d5e515677",
                "location": "62d2eb3d75156700663c8367",
                "mission": "62d2f09c751567007abb1988",
                "rate": 7.37,
                "rarity": "rare",
                "rotation": "b",
                "stage": [
                    "4"
                ],
                "id": "62d3524d650ea601a7ad0840"
            },
            {
                "type": "mission",
                "item": "54a74454e779892d5e515677",
                "location": "62d2eb3d75156700663c8367",
                "mission": "62d2f09c751567007abb1988",
                "rate": 30.56,
                "rarity": "uncommon",
                "rotation": "b",
                "stage": [
                    "final"
                ],
                "id": "62d3524d650ea601a7ad0841"
            },
            {
                "type": "mission",
                "item": "54a74454e779892d5e515677",
                "mission": "62d2f097751567007abb1974",
                "rate": 2.01,
                "rarity": "rare",
                "rotation": "c",
                "id": "62d3524d650ea601a7ad0842"
            },
            {
                "type": "mission",
                "item": "54a74454e779892d5e515677",
                "mission": "62d2f099751567007abb197e",
                "rate": 2.01,
                "rarity": "rare",
                "rotation": "c",
                "id": "62d3524d650ea601a7ad0843"
            },
            {
                "type": "mission",
                "item": "54a74454e779892d5e515677",
                "mission": "62d2f0a2751567007abb1989",
                "rate": 2.01,
                "rarity": "rare",
                "rotation": "c",
                "id": "62d3524d650ea601a7ad0844"
            },
            {
                "type": "mission",
                "item": "54a74454e779892d5e515677",
                "mission": "62d2f098751567007abb197a",
                "rate": 2.01,
                "rarity": "rare",
                "rotation": "c",
                "id": "62d3524d650ea601a7ad0845"
            },
            {
                "type": "mission",
                "item": "54a74454e779892d5e515677",
                "mission": "62d2f07e751567007abb1972",
                "rate": 2.01,
                "rarity": "rare",
                "rotation": "c",
                "id": "62d3524d650ea601a7ad0846"
            },
            {
                "type": "mission",
                "item": "54a74454e779892d5e515677",
                "mission": "62d2f049751567007abb1955",
                "rate": 2.01,
                "rarity": "rare",
                "rotation": "c",
                "id": "62d3524d650ea601a7ad0847"
            },
            {
                "type": "mission",
                "item": "54a74454e779892d5e515677",
                "mission": "62d2f0a2751567007abb198a",
                "rate": 2.01,
                "rarity": "rare",
                "rotation": "c",
                "id": "62d3524d650ea601a7ad0848"
            },
            {
                "type": "mission",
                "item": "54a74454e779892d5e515677",
                "mission": "62d2f0f4751567007abb1998",
                "rate": 2.01,
                "rarity": "rare",
                "rotation": "c",
                "id": "62d3524d650ea601a7ad0849"
            },
            {
                "type": "npc",
                "item": "54a74454e779892d5e515677",
                "npc": "62d2f040751567007abb1905",
                "rate": 0.33,
                "rarity": "uncommon",
                "id": "62d3524d650ea601a7ad084a"
            },
            {
                "type": "npc",
                "item": "54a74454e779892d5e515677",
                "npc": "62d2f035751567007abb189b",
                "rate": 0.33,
                "rarity": "uncommon",
                "id": "62d3524d650ea601a7ad084b"
            },
            {
                "type": "npc",
                "item": "54a74454e779892d5e515677",
                "npc": "62d2f039751567007abb18c2",
                "rate": 0.33,
                "rarity": "uncommon",
                "id": "62d3524d650ea601a7ad084c"
            },
            {
                "type": "npc",
                "item": "54a74454e779892d5e515677",
                "npc": "62d2f03d751567007abb18e6",
                "rate": 0.37,
                "rarity": "rare",
                "id": "62d3524d650ea601a7ad084d"
            },
            {
                "type": "npc",
                "item": "54a74454e779892d5e515677",
                "npc": "62d2f01d751567007abb17de",
                "rate": 0.33,
                "rarity": "uncommon",
                "id": "62d3524d650ea601a7ad084e"
            },
            {
                "type": "npc",
                "item": "54a74454e779892d5e515677",
                "npc": "62d2f004751567007abb170b",
                "rate": 0.33,
                "rarity": "uncommon",
                "id": "62d3524d650ea601a7ad084f"
            },
            {
                "type": "npc",
                "item": "54a74454e779892d5e515677",
                "npc": "62d2eff6751567007abb1697",
                "rate": 0.33,
                "rarity": "uncommon",
                "id": "62d3524d650ea601a7ad0850"
            },
            {
                "type": "npc",
                "item": "54a74454e779892d5e515677",
                "npc": "62d2effd751567007abb16d3",
                "rate": 0.22,
                "rarity": "rare",
                "id": "62d3524d650ea601a7ad0851"
            },
            {
                "type": "npc",
                "item": "54a74454e779892d5e515677",
                "npc": "62d2f048751567007abb1953",
                "rate": 0.33,
                "rarity": "uncommon",
                "id": "62d3524d650ea601a7ad0852"
            },
            {
                "type": "npc",
                "item": "54a74454e779892d5e515677",
                "npc": "62d2f031751567007abb187e",
                "rate": 0.74,
                "rarity": "rare",
                "id": "62d3524d650ea601a7ad0853"
            },
            {
                "type": "npc",
                "item": "54a74454e779892d5e515677",
                "npc": "62d2f02c751567007abb1855",
                "rate": 4.42,
                "rarity": "rare",
                "id": "62d3524d650ea601a7ad0855"
            },
            {
                "type": "npc",
                "item": "54a74454e779892d5e515677",
                "npc": "62d2eff5751567007abb1689",
                "rate": 0.33,
                "rarity": "uncommon",
                "id": "62d3524d650ea601a7ad0856"
            },
            {
                "type": "npc",
                "item": "54a74454e779892d5e515677",
                "npc": "62d2f03e751567007abb18f4",
                "rate": 4.42,
                "rarity": "rare",
                "id": "62d3524d650ea601a7ad0857"
            },
            {
                "type": "npc",
                "item": "54a74454e779892d5e515677",
                "npc": "62d2f041751567007abb1915",
                "rate": 22.92,
                "rarity": "uncommon",
                "id": "62d3524d650ea601a7ad0859"
            },
            {
                "type": "npc",
                "item": "54a74454e779892d5e515677",
                "npc": "62d2f024751567007abb1811",
                "rate": 5.64,
                "rarity": "rare",
                "id": "62d3524d650ea601a7ad085a"
            },
            {
                "type": "npc",
                "item": "54a74454e779892d5e515677",
                "npc": "62d2f023751567007abb1806",
                "rate": 0.55,
                "rarity": "uncommon",
                "id": "62d3524d650ea601a7ad085e"
            },
            {
                "type": "npc",
                "item": "54a74454e779892d5e515677",
                "npc": "62d2f033751567007abb188a",
                "rate": 0.55,
                "rarity": "uncommon",
                "id": "62d3524d650ea601a7ad085f"
            },
            {
                "type": "npc",
                "item": "54a74454e779892d5e515677",
                "npc": "62d2f011751567007abb177f",
                "rate": 0.55,
                "rarity": "uncommon",
                "id": "62d3524d650ea601a7ad0860"
            },
            {
                "type": "npc",
                "item": "54a74454e779892d5e515677",
                "npc": "62d2f011751567007abb1779",
                "rate": 4.42,
                "rarity": "rare",
                "id": "62d3524d650ea601a7ad0863"
            },
            {
                "type": "npc",
                "item": "54a74454e779892d5e515677",
                "npc": "62d2effa751567007abb16bb",
                "rate": 0.37,
                "rarity": "rare",
                "id": "62d3524d650ea601a7ad0864"
            },
            {
                "type": "npc",
                "item": "54a74454e779892d5e515677",
                "npc": "62d2f019751567007abb17c1",
                "rate": 0.22,
                "rarity": "rare",
                "id": "62d3524d650ea601a7ad0865"
            },
            {
                "type": "npc",
                "item": "54a74454e779892d5e515677",
                "npc": "62d2f025751567007abb1814",
                "rate": 0.33,
                "rarity": "uncommon",
                "id": "62d3524d650ea601a7ad0866"
            },
            {
                "type": "npc",
                "item": "54a74454e779892d5e515677",
                "npc": "62d2f027751567007abb1822",
                "rate": 0.37,
                "rarity": "rare",
                "id": "62d3524d650ea601a7ad0868"
            },
            {
                "type": "npc",
                "item": "54a74454e779892d5e515677",
                "npc": "62d2f01c751567007abb17db",
                "rate": 0.33,
                "rarity": "uncommon",
                "id": "62d3524d650ea601a7ad0869"
            },
            {
                "type": "npc",
                "item": "54a74454e779892d5e515677",
                "npc": "62d2f02d751567007abb185a",
                "rate": 0.97,
                "rarity": "rare",
                "id": "62d3524d650ea601a7ad086a"
            },
            {
                "type": "npc",
                "item": "54a74454e779892d5e515677",
                "npc": "62d2f003751567007abb1709",
                "rate": 0.37,
                "rarity": "rare",
                "id": "62d3524d650ea601a7ad086c"
            },
            {
                "type": "npc",
                "item": "54a74454e779892d5e515677",
                "npc": "62d2effa751567007abb16b8",
                "rate": 0.74,
                "rarity": "rare",
                "id": "62d3524d650ea601a7ad086d"
            },
            {
                "type": "npc",
                "item": "54a74454e779892d5e515677",
                "npc": "62d2eff8751567007abb16ac",
                "rate": 0.18,
                "rarity": "rare",
                "id": "62d3524d650ea601a7ad086e"
            },
            {
                "type": "npc",
                "item": "54a74454e779892d5e515677",
                "npc": "62d2eff8751567007abb16ac",
                "rate": 0.74,
                "rarity": "rare",
                "id": "62d3524d650ea601a7ad086f"
            },
            {
                "type": "npc",
                "item": "54a74454e779892d5e515677",
                "npc": "62d2f03d751567007abb18e7",
                "rate": 0.74,
                "rarity": "rare",
                "id": "62d3524d650ea601a7ad0870"
            },
            {
                "type": "npc",
                "item": "54a74454e779892d5e515677",
                "npc": "62d2f00b751567007abb1750",
                "rate": 0.74,
                "rarity": "rare",
                "id": "62d3524d650ea601a7ad0871"
            },
            {
                "type": "npc",
                "item": "54a74454e779892d5e515677",
                "npc": "62d2f01f751567007abb17ee",
                "rate": 0.74,
                "rarity": "rare",
                "id": "62d3524d650ea601a7ad0872"
            },
            {
                "type": "npc",
                "item": "54a74454e779892d5e515677",
                "npc": "62d2f009751567007abb1738",
                "rate": 0.74,
                "rarity": "rare",
                "id": "62d3524d650ea601a7ad0873"
            },
            {
                "type": "npc",
                "item": "54a74454e779892d5e515677",
                "npc": "62d2f000751567007abb16ee",
                "rate": 0.37,
                "rarity": "rare",
                "id": "62d3524d650ea601a7ad0874"
            },
            {
                "type": "npc",
                "item": "54a74454e779892d5e515677",
                "npc": "62d2f000751567007abb16ee",
                "rate": 0.74,
                "rarity": "rare",
                "id": "62d3524d650ea601a7ad0875"
            },
            {
                "type": "npc",
                "item": "54a74454e779892d5e515677",
                "npc": "62d2f034751567007abb1897",
                "rate": 0.37,
                "rarity": "rare",
                "id": "62d3524d650ea601a7ad0876"
            },
            {
                "type": "npc",
                "item": "54a74454e779892d5e515677",
                "npc": "62d2f034751567007abb1897",
                "rate": 0.74,
                "rarity": "rare",
                "id": "62d3524d650ea601a7ad0877"
            },
            {
                "type": "npc",
                "item": "54a74454e779892d5e515677",
                "npc": "62d2f030751567007abb1871",
                "rate": 0.37,
                "rarity": "rare",
                "id": "62d3524d650ea601a7ad0878"
            },
            {
                "type": "npc",
                "item": "54a74454e779892d5e515677",
                "npc": "62d2f030751567007abb1871",
                "rate": 0.74,
                "rarity": "rare",
                "id": "62d3524d650ea601a7ad0879"
            },
            {
                "type": "npc",
                "item": "54a74454e779892d5e515677",
                "npc": "62d2effb751567007abb16c2",
                "rate": 0.18,
                "rarity": "rare",
                "id": "62d3524d650ea601a7ad087a"
            },
            {
                "type": "npc",
                "item": "54a74454e779892d5e515677",
                "npc": "62d2effb751567007abb16c2",
                "rate": 0.74,
                "rarity": "rare",
                "id": "62d3524d650ea601a7ad087b"
            },
            {
                "type": "npc",
                "item": "54a74454e779892d5e515677",
                "npc": "62d2f02f751567007abb186d",
                "rate": 0.37,
                "rarity": "rare",
                "id": "62d3524d650ea601a7ad087c"
            },
            {
                "type": "npc",
                "item": "54a74454e779892d5e515677",
                "npc": "62d2f02f751567007abb186d",
                "rate": 0.74,
                "rarity": "rare",
                "id": "62d3524d650ea601a7ad087d"
            },
            {
                "type": "npc",
                "item": "54a74454e779892d5e515677",
                "npc": "62d2f004751567007abb1710",
                "rate": 0.18,
                "rarity": "rare",
                "id": "62d3524d650ea601a7ad087e"
            },
            {
                "type": "npc",
                "item": "54a74454e779892d5e515677",
                "npc": "62d2f012751567007abb1785",
                "rate": 0.18,
                "rarity": "rare",
                "id": "62d3524d650ea601a7ad087f"
            },
            {
                "type": "npc",
                "item": "54a74454e779892d5e515677",
                "npc": "62d2f03a751567007abb18c6",
                "rate": 0.37,
                "rarity": "rare",
                "id": "62d3524d650ea601a7ad0880"
            },
            {
                "type": "npc",
                "item": "54a74454e779892d5e515677",
                "npc": "62d2f00c751567007abb1756",
                "rate": 0.18,
                "rarity": "rare",
                "id": "62d3524d650ea601a7ad0881"
            },
            {
                "type": "npc",
                "item": "54a74454e779892d5e515677",
                "npc": "62d2f01f751567007abb17ea",
                "rate": 0.18,
                "rarity": "rare",
                "id": "62d3524d650ea601a7ad0882"
            },
            {
                "type": "npc",
                "item": "54a74454e779892d5e515677",
                "npc": "62d2f025751567007abb1815",
                "rate": 10.26,
                "rarity": "uncommon",
                "id": "62d3524d650ea601a7ad0883"
            },
            {
                "type": "mission",
                "item": "54a74454e779892d5e515677",
                "location": "62d2eb6275156700663c8402",
                "mission": "62d2f063751567007abb1961",
                "rate": 0.34,
                "rarity": "legendary",
                "id": "62fd5dbfb8a9cc004ec50969"
            },
            {
                "type": "npc",
                "item": "54a74454e779892d5e515677",
                "npc": "62d2f014751567007abb1794",
                "rate": 0.33,
                "rarity": "uncommon",
                "id": "633e2e90f570d1079c2e361e"
            },
            {
                "type": "npc",
                "item": "54a74454e779892d5e515677",
                "npc": "62d2f019751567007abb17c3",
                "rate": 0.74,
                "rarity": "rare",
                "id": "633e2e90f570d1079c2e361f"
            },
            {
                "type": "npc",
                "item": "54a74454e779892d5e515677",
                "npc": "62d2f022751567007abb17ff",
                "rate": 0.33,
                "rarity": "uncommon",
                "id": "633e2e90f570d1079c2e3622"
            },
            {
                "type": "npc",
                "item": "54a74454e779892d5e515677",
                "npc": "632292a6dd457f0084f1a40e",
                "rate": 0.33,
                "rarity": "uncommon",
                "id": "633e2e90f570d1079c2e3623"
            },
            {
                "type": "npc",
                "item": "54a74454e779892d5e515677",
                "npc": "632292a0dd457f0084f1a409",
                "rate": 0.37,
                "rarity": "rare",
                "id": "633e2e90f570d1079c2e3624"
            },
            {
                "type": "npc",
                "item": "54a74454e779892d5e515677",
                "npc": "62d2f01e751567007abb17e0",
                "rate": 0.23,
                "rarity": "rare",
                "id": "633e3203f570d107d2a968e7"
            },
            {
                "type": "npc",
                "item": "54a74454e779892d5e515677",
                "npc": "62d2f008751567007abb1731",
                "rate": 0.37,
                "rarity": "rare",
                "id": "63ee050b10125412198827de"
            },
            {
                "type": "mission",
                "item": "54a74454e779892d5e515677",
                "location": "62d2eb7275156700663c8443",
                "mission": "62d2f0a2751567007abb198b",
                "rate": 4.51,
                "rarity": "rare",
                "rotation": "c",
                "id": "63f103e307ebe90061f4bb0b"
            },
            {
                "type": "mission",
                "item": "54a74454e779892d5e515677",
                "location": "62d2eb4f75156700663c83b1",
                "mission": "62d2f0a2751567007abb198b",
                "rate": 4.51,
                "rarity": "rare",
                "rotation": "c",
                "id": "63f103e307ebe90061f4bb0c"
            },
            {
                "type": "mission",
                "item": "54a74454e779892d5e515677",
                "location": "62d2f0fb751567007abb19b0",
                "mission": "62d2f0a2751567007abb198b",
                "rate": 2.26,
                "rarity": "rare",
                "rotation": "c",
                "event": true,
                "id": "63f103e307ebe90061f4bb0d"
            },
            {
                "type": "mission",
                "item": "54a74454e779892d5e515677",
                "location": "62d2f104751567007abb1a03",
                "mission": "62d2f0a2751567007abb198b",
                "rate": 2.26,
                "rarity": "rare",
                "rotation": "c",
                "event": true,
                "id": "63f103e307ebe90061f4bb0e"
            },
            {
                "type": "mission",
                "item": "54a74454e779892d5e515677",
                "location": "62d2eb3f75156700663c8370",
                "mission": "62d2f0a2751567007abb198b",
                "rate": 2.26,
                "rarity": "rare",
                "rotation": "c",
                "id": "63f103e307ebe90061f4bb0f"
            },
            {
                "type": "mission",
                "item": "54a74454e779892d5e515677",
                "location": "62d2eb4975156700663c8398",
                "mission": "62d2f0a2751567007abb198b",
                "rate": 2.26,
                "rarity": "rare",
                "rotation": "c",
                "id": "63f103e307ebe90061f4bb10"
            },
            {
                "type": "mission",
                "item": "54a74454e779892d5e515677",
                "location": "62d2eb5f75156700663c83f2",
                "mission": "62d2f0a2751567007abb198b",
                "rate": 2.26,
                "rarity": "rare",
                "rotation": "c",
                "id": "63f103e307ebe90061f4bb11"
            },
            {
                "type": "mission",
                "item": "54a74454e779892d5e515677",
                "location": "62d2eb4975156700663c8399",
                "mission": "62d2f0a2751567007abb198b",
                "rate": 2.26,
                "rarity": "rare",
                "rotation": "c",
                "id": "63f103e307ebe90061f4bb12"
            },
            {
                "type": "mission",
                "item": "54a74454e779892d5e515677",
                "location": "62d2f103751567007abb19fb",
                "mission": "62d2f0a2751567007abb198b",
                "rate": 2.26,
                "rarity": "rare",
                "rotation": "c",
                "event": true,
                "id": "63f103e307ebe90061f4bb13"
            },
            {
                "type": "mission",
                "item": "54a74454e779892d5e515677",
                "location": "62d2f103751567007abb19ff",
                "mission": "62d2f0a2751567007abb198b",
                "rate": 4.51,
                "rarity": "rare",
                "rotation": "c",
                "event": true,
                "id": "63f103e307ebe90061f4bb14"
            },
            {
                "type": "mission",
                "item": "54a74454e779892d5e515677",
                "location": "62d2eb4d75156700663c83a8",
                "mission": "62d2f0a2751567007abb198b",
                "rate": 2.26,
                "rarity": "rare",
                "rotation": "c",
                "id": "63f103e307ebe90061f4bb15"
            },
            {
                "type": "mission",
                "item": "54a74454e779892d5e515677",
                "location": "62d2eb3975156700663c835a",
                "mission": "62d2f0a2751567007abb198b",
                "rate": 4.51,
                "rarity": "rare",
                "rotation": "c",
                "id": "63f103e307ebe90061f4bb16"
            },
            {
                "type": "mission",
                "item": "54a74454e779892d5e515677",
                "location": "62d2eb3d75156700663c8368",
                "mission": "62d2f0a2751567007abb198b",
                "rate": 2.26,
                "rarity": "rare",
                "rotation": "c",
                "id": "63f103e307ebe90061f4bb17"
            },
            {
                "type": "mission",
                "item": "54a74454e779892d5e515677",
                "location": "62d2eb6e75156700663c8432",
                "mission": "62d2f0a2751567007abb198b",
                "rate": 2.26,
                "rarity": "rare",
                "rotation": "c",
                "id": "63f103e307ebe90061f4bb18"
            },
            {
                "type": "npc",
                "item": "54a74454e779892d5e515677",
                "npc": "62d2f008751567007abb172e",
                "rate": 0.33,
                "rarity": "uncommon",
                "id": "63f103e307ebe90061f4bb19"
            },
            {
                "type": "npc",
                "item": "54a74454e779892d5e515677",
                "npc": "62d2f013751567007abb178f",
                "rate": 11.06,
                "rarity": "uncommon",
                "id": "63f103e307ebe90061f4bb1a"
            },
            {
                "type": "npc",
                "item": "54a74454e779892d5e515677",
                "npc": "62d2f013751567007abb178f",
                "rate": 0.55,
                "rarity": "uncommon",
                "id": "63f103e307ebe90061f4bb1b"
            },
            {
                "type": "npc",
                "item": "54a74454e779892d5e515677",
                "npc": "62d2f028751567007abb1829",
                "rate": 0.33,
                "rarity": "uncommon",
                "id": "63f103e307ebe90061f4bb1c"
            },
            {
                "type": "mission",
                "item": "54a74454e779892d5e515677",
                "location": "644b01ab7ec190004dbb80c1",
                "mission": "644b00467ec1900044b97746",
                "rate": 0.52,
                "rarity": "legendary",
                "modifier": "normal",
                "id": "644b04e97ec19000567fa3f6"
            },
            {
                "type": "mission",
                "item": "54a74454e779892d5e515677",
                "location": "644b01ab7ec190004dbb80c1",
                "mission": "644b00457ec1900044b9773f",
                "rate": 0.52,
                "rarity": "legendary",
                "modifier": "normal",
                "id": "644b04e97ec19000567fa3f7"
            },
            {
                "type": "mission",
                "item": "54a74454e779892d5e515677",
                "location": "62d2eb3d75156700663c8367",
                "mission": "62d2f09c751567007abb1988",
                "rate": 7.52,
                "rarity": "rare",
                "rotation": "b",
                "stage": [
                    "2",
                    "3"
                ],
                "id": "644b04e97ec19000567fa3f8"
            }
        ]
    }
}