{
    "payload": {
        "dropsources": [
            {
                "type": "relic",
                "item": "559daae0e779897b5273b716",
                "relic": "6054dd235221e30057500f2b",
                "rates": {
                    "intact": 25.33,
                    "exceptional": 23.33,
                    "flawless": 20,
                    "radiant": 16.67
                },
                "rarity": "common",
                "id": "62d2f23b7515670098198581"
            },
            {
                "type": "relic",
                "item": "559daae0e779897b5273b716",
                "relic": "6054dd355221e30057500f39",
                "rates": {
                    "intact": 25.33,
                    "exceptional": 23.33,
                    "flawless": 20,
                    "radiant": 16.67
                },
                "rarity": "common",
                "id": "62d2f23b7515670098198582"
            },
            {
                "type": "relic",
                "item": "559daae0e779897b5273b716",
                "relic": "6054dd505221e30057500f4e",
                "rates": {
                    "intact": 25.33,
                    "exceptional": 23.33,
                    "flawless": 20,
                    "radiant": 16.67
                },
                "rarity": "common",
                "id": "62d2f23b7515670098198583"
            },
            {
                "type": "relic",
                "item": "559daae0e779897b5273b716",
                "relic": "6054ddc55221e30057500fbf",
                "rates": {
                    "intact": 25.33,
                    "exceptional": 23.33,
                    "flawless": 20,
                    "radiant": 16.67
                },
                "rarity": "common",
                "id": "62d2f23b7515670098198584"
            },
            {
                "type": "relic",
                "item": "559daae0e779897b5273b716",
                "relic": "6054de625221e3005750106c",
                "rates": {
                    "intact": 25.33,
                    "exceptional": 23.33,
                    "flawless": 20,
                    "radiant": 16.67
                },
                "rarity": "common",
                "id": "62d2f23b7515670098198585"
            },
            {
                "type": "relic",
                "item": "559daae0e779897b5273b716",
                "relic": "644b00227ec1900044b97726",
                "rates": {
                    "intact": 25.33,
                    "exceptional": 23.33,
                    "flawless": 20,
                    "radiant": 16.67
                },
                "rarity": "common",
                "id": "644b04eb7ec19000567fa64c"
            }
        ]
    }
}