{
    "payload": {
        "dropsources": [
            {
                "type": "npc",
                "item": "56fdbd5d2e26966de716e432",
                "npc": "62d2f021751567007abb17fa",
                "rate": 0.5,
                "rarity": "common",
                "id": "62d2f24175156700981995b2"
            },
            {
                "type": "npc",
                "item": "56fdbd5d2e26966de716e432",
                "npc": "62d2f01b751567007abb17d6",
                "rate": 0.5,
                "rarity": "common",
                "id": "62d2f24175156700981995b3"
            },
            {
                "type": "npc",
                "item": "56fdbd5d2e26966de716e432",
                "npc": "62d2effc751567007abb16d0",
                "rate": 0.5,
                "rarity": "common",
                "id": "62d2f24175156700981995b4"
            },
            {
                "type": "npc",
                "item": "56fdbd5d2e26966de716e432",
                "npc": "62d2f001751567007abb16f9",
                "rate": 0.5,
                "rarity": "common",
                "id": "62d2f24175156700981995b5"
            },
            {
                "type": "npc",
                "item": "56fdbd5d2e26966de716e432",
                "npc": "62d2f022751567007abb1801",
                "rate": 0.5,
                "rarity": "common",
                "id": "62d2f24175156700981995b6"
            },
            {
                "type": "npc",
                "item": "56fdbd5d2e26966de716e432",
                "npc": "62d2f01f751567007abb17ec",
                "rate": 0.5,
                "rarity": "common",
                "id": "62d2f24175156700981995b7"
            }
        ]
    }
}